.gitignore
COPYING.LESSER.txt
MANIFEST.in
README.rst
setup.py
docs/Makefile
docs/conf.py
docs/glossary.rst
docs/glossary_include.rst
docs/index.rst
docs/index_include.rst
score/__init__.py
score.projects.egg-info/PKG-INFO
score.projects.egg-info/SOURCES.txt
score.projects.egg-info/dependency_links.txt
score.projects.egg-info/entry_points.txt
score.projects.egg-info/namespace_packages.txt
score.projects.egg-info/not-zip-safe
score.projects.egg-info/requires.txt
score.projects.egg-info/top_level.txt
score/projects/__init__.py
score/projects/_init.py
score/projects/_setup.py
score/projects/_tpl.py
score/projects/cli.py
score/projects/project.py
score/projects/scaffolds/minimal/README.rst
score/projects/scaffolds/minimal/local.conf
score/projects/scaffolds/minimal/setup.py
score/projects/scaffolds/minimal/__PACKAGE_NAME__/__init__.py
score/projects/scaffolds/minimal/__PACKAGE_NAME__/_init.py